matplotlib_cern/__init__.py
matplotlib_cern/template.py
matplotlib_cern-0.1.2.dist-info/LICENSE
matplotlib_cern-0.1.2.dist-info/METADATA
matplotlib_cern-0.1.2.dist-info/WHEEL
matplotlib_cern-0.1.2.dist-info/top_level.txt
matplotlib_cern-0.1.2.dist-info/RECORD
