Metadata-Version: 2.1
Name: matplotlib-cern
Version: 0.1.2
Summary: A matplotlib template package for CERN plots
Home-page: UNKNOWN
Author: Georgios Christou
License: UNKNOWN
Platform: UNKNOWN
License-File: LICENSE
Requires-Dist: matplotlib
